{
  "ratingQuestions": [
    {
      "identifier": "Number",
      "category": "AdditionalInfo",
      "fieldLabel": "Driver License Number",
      "fieldType": "Data Entry",
      "fieldLength": "25",
      "required": "Y",
      "tooltip": "",
      "displayOrder": "3",
      "hasAdditional": "false",
      "validationMessage": "Please enter a valid drivers license number",
      "validationPattern": "^(?!.{26,})[a-zA-Z0-9._-]+$",
      "options": []
    },
    {
      "identifier": "State",
      "category": "AdditionalInfo",
      "fieldLabel": "Driver License State",
      "fieldType": "Selection",
      "fieldLength": "",
      "required": "Y",
      "tooltip": "",
      "displayOrder": "2",
      "hasAdditional": "false",
      "options": [
        {
          "description": "Alabama",
          "code": "AL"
        },
        {
          "description": "Alaska",
          "code": "AK"
        },
        {
          "description": "Alberta",
          "code": "AB"
        },
        {
          "description": "American Samoa",
          "code": "AS"
        },
        {
          "description": "Arizona",
          "code": "AZ"
        },
        {
          "description": "Arkansas",
          "code": "AR"
        },
        {
          "description": "Armed Forces Atlantic Post Office Box",
          "code": "AA"
        },
        {
          "description": "Armed Forces Europe Post Office Box",
          "code": "AE"
        },
        {
          "description": "Armed Forces Pacific Post Office Box",
          "code": "AP"
        },
        {
          "description": "British Columbia",
          "code": "BC"
        },
        {
          "description": "California",
          "code": "CA"
        },
        {
          "description": "Colorado",
          "code": "CO"
        },
        {
          "description": "Connecticut",
          "code": "CT"
        },
        {
          "description": "Delaware",
          "code": "DE"
        },
        {
          "description": "District of Columbia",
          "code": "DC"
        },
        {
          "description": "Federated States of Micro",
          "code": "FM"
        },
        {
          "description": "Florida",
          "code": "FL"
        },
        {
          "description": "Georgia",
          "code": "GA"
        },
        {
          "description": "Guam",
          "code": "GU"
        },
        {
          "description": "Hawaii",
          "code": "HI"
        },
        {
          "description": "Idaho",
          "code": "ID"
        },
        {
          "description": "Illinois",
          "code": "IL"
        },
        {
          "description": "Indiana",
          "code": "IN"
        },
        {
          "description": "Iowa",
          "code": "IA"
        },
        {
          "description": "Kansas",
          "code": "KS"
        },
        {
          "description": "Kentucky",
          "code": "KY"
        },
        {
          "description": "Louisiana",
          "code": "LA"
        },
        {
          "description": "Maine",
          "code": "ME"
        },
        {
          "description": "Manitoba",
          "code": "MB"
        },
        {
          "description": "Marshall Islands",
          "code": "MH"
        },
        {
          "description": "Maryland",
          "code": "MD"
        },
        {
          "description": "Massachusetts",
          "code": "MA"
        },
        {
          "description": "Michigan",
          "code": "MI"
        },
        {
          "description": "Minnesota",
          "code": "MN"
        },
        {
          "description": "Mississippi",
          "code": "MS"
        },
        {
          "description": "Missouri",
          "code": "MO"
        },
        {
          "description": "Montana",
          "code": "MT"
        },
        {
          "description": "Nebraska",
          "code": "NE"
        },
        {
          "description": "Nevada",
          "code": "NV"
        },
        {
          "description": "New Brunswick",
          "code": "NB"
        },
        {
          "description": "New Hampshire",
          "code": "NH"
        },
        {
          "description": "New Jersey",
          "code": "NJ"
        },
        {
          "description": "New Mexico",
          "code": "NM"
        },
        {
          "description": "New York",
          "code": "NY"
        },
        {
          "description": "Newfoundland",
          "code": "NF"
        },
        {
          "description": "North Carolina",
          "code": "NC"
        },
        {
          "description": "North Dakota",
          "code": "ND"
        },
        {
          "description": "Northern Mariana Islands",
          "code": "MP"
        },
        {
          "description": "Northwest Territories",
          "code": "NT"
        },
        {
          "description": "Northwest Territory",
          "code": "NW"
        },
        {
          "description": "Not Applicable",
          "code": "NA"
        },
        {
          "description": "Nova Scotia",
          "code": "NS"
        },
        {
          "description": "Nunavut",
          "code": "NU"
        },
        {
          "description": "Ohio",
          "code": "OH"
        },
        {
          "description": "Oklahoma",
          "code": "OK"
        },
        {
          "description": "Ontario",
          "code": "ON"
        },
        {
          "description": "Oregon",
          "code": "OR"
        },
        {
          "description": "Palau Islands",
          "code": "PW"
        },
        {
          "description": "Pennsylvania",
          "code": "PA"
        },
        {
          "description": "Prince Edward Island",
          "code": "PE"
        },
        {
          "description": "Puerto Rico",
          "code": "PR"
        },
        {
          "description": "Quebec",
          "code": "QC"
        },
        {
          "description": "Rhode Island",
          "code": "RI"
        },
        {
          "description": "Saskatchewan",
          "code": "SK"
        },
        {
          "description": "South Carolina",
          "code": "SC"
        },
        {
          "description": "South Dakota",
          "code": "SD"
        },
        {
          "description": "Tennessee",
          "code": "TN"
        },
        {
          "description": "Texas",
          "code": "TX"
        },
        {
          "description": "Utah",
          "code": "UT"
        },
        {
          "description": "Vermont",
          "code": "VT"
        },
        {
          "description": "Virgin Islands",
          "code": "VI"
        },
        {
          "description": "Virginia",
          "code": "VA"
        },
        {
          "description": "Washington",
          "code": "WA"
        },
        {
          "description": "West Virginia",
          "code": "WV"
        },
        {
          "description": "Wisconsin",
          "code": "WI"
        },
        {
          "description": "Wyoming",
          "code": "WY"
        },
        {
          "description": "Yukon",
          "code": "YT"
        }
      ]
    },
    {
      "identifier": "Occupation",
      "category": "AdditionalInfo",
      "fieldLabel": "Occupation",
      "fieldType": "Selection",
      "fieldLength": "",
      "required": "Y",
      "tooltip": "",
      "displayOrder": "4",
      "hasAdditional": "false",
      "options": [
        {
          "description": "Engineer",
          "code": "200"
        },
        {
          "description": "Farmer/Rancher",
          "code": "550"
        },
        {
          "description": "Full Time Student",
          "code": "350"
        },
        {
          "description": "Homemaker",
          "code": "800"
        },
        {
          "description": "Politician",
          "code": "150"
        },
        {
          "description": "Retired",
          "code": "400"
        },
        {
          "description": "Sales",
          "code": "450"
        },
        {
          "description": "Self Employed - Works at Home",
          "code": "600"
        },
        {
          "description": "Self Employed - Works Outside of Home",
          "code": "650"
        },
        {
          "description": "Unemployed",
          "code": "700"
        },
        {
          "description": "Other",
          "code": "500"
        }
      ]
    },
    {
      "identifier": "VIN",
      "category": "AdditionalInfo",
      "fieldLabel": "VIN",
      "fieldType": "Data Entry",
      "fieldLength": "17",
      "required": "Y",
      "tooltip": "",
      "displayOrder": "1",
      "hasAdditional": "false",
      "validationMessage": "VIN number is invalid",
      "validationPattern": "^[A-HJ-NPR-Za-hj-npr-z\\d]{8}[\\dX][A-HJ-NPR-Za-hj-npr-z\\d]{2}\\d{6}$",
      "options": []
    }
  ]
}